{"1536608020.8397279": {"fight winner": null, "player": "Joh Kirby", "opponent current health": 26.060121163502536, "fight over": false, "player attack damage": 3.64917811324357, "player health": 112.371, "opponent attack damage": null, "opponent name": "C3-PO"}, "1536608022.0959485": {"fight winner": null, "player": "Joh Kirby", "opponent current health": 14.058708317405681, "fight over": false, "player attack damage": 4.74874211269767, "player health": 110.241, "opponent attack damage": null, "opponent name": "C3-PO"}, "1536608023.1151693": {"fight winner": null, "player": "Joh Kirby", "opponent current health": 8.527389739487873, "fight over": false, "player attack damage": 5.531318577917809, "player health": 108.144, "opponent attack damage": null, "opponent name": "C3-PO"}, "1536608018.1628575": {"fight winner": null, "player": "Joh Kirby", "opponent current health": 50.2831820111528, "fight over": false, "player attack damage": null, "player health": 119.3, "opponent attack damage": 3.391, "opponent name": "C3-PO"}, "1536608015.0597696": {"fight winner": null, "player": "Joh Kirby", "opponent current health": 60.0, "fight over": false, "player attack damage": null, "player health": 119.3, "opponent attack damage": null, "opponent name": "C3-PO"}, "1536608023.6748233": {"fight winner": "Joh Kirby", "player": "Joh Kirby", "opponent current health": -0.3386129136831588, "fight over": true, "player attack damage": 8.866002653171032, "player health": 103.863, "opponent attack damage": null, "opponent name": "C3-PO"}, "1536608018.1560113": {"fight winner": null, "player": "Joh Kirby", "opponent current health": 50.2831820111528, "fight over": false, "player attack damage": 9.716817988847193, "player health": 119.3, "opponent attack damage": null, "opponent name": "C3-PO"}, "1536608018.6714425": {"fight winner": null, "player": "Joh Kirby", "opponent current health": 45.886075723491956, "fight over": false, "player attack damage": 4.397106287660849, "player health": 115.90899999999999, "opponent attack damage": null, "opponent name": "C3-PO"}, "1536608019.429539": {"fight winner": null, "player": "Joh Kirby", "opponent current health": 36.93274273503178, "fight over": false, "player attack damage": 8.953332988460172, "player health": 115.90899999999999, "opponent attack damage": null, "opponent name": "C3-PO"}, "1536608021.0768864": {"fight winner": null, "player": "Joh Kirby", "opponent current health": 26.060121163502536, "fight over": false, "player attack damage": null, "player health": 112.371, "opponent attack damage": 2.13, "opponent name": "C3-PO"}, "1536608021.5878484": {"fight winner": null, "player": "Joh Kirby", "opponent current health": 18.80745043010335, "fight over": false, "player attack damage": 7.252670733399187, "player health": 110.241, "opponent attack damage": null, "opponent name": "C3-PO"}, "1536608022.6095726": {"fight winner": null, "player": "Joh Kirby", "opponent current health": 14.058708317405681, "fight over": false, "player attack damage": null, "player health": 110.241, "opponent attack damage": 2.097, "opponent name": "C3-PO"}, "1536608023.4163413": {"fight winner": null, "player": "Joh Kirby", "opponent current health": 8.527389739487873, "fight over": false, "player attack damage": null, "player health": 108.144, "opponent attack damage": 4.281, "opponent name": "C3-PO"}, "1536608020.1934218": {"fight winner": null, "player": "Joh Kirby", "opponent current health": 29.70929927674611, "fight over": false, "player attack damage": 7.22344345828567, "player health": 115.90899999999999, "opponent attack damage": null, "opponent name": "C3-PO"}, "1536608020.3315952": {"fight winner": null, "player": "Joh Kirby", "opponent current health": 29.70929927674611, "fight over": false, "player attack damage": null, "player health": 115.90899999999999, "opponent attack damage": 3.538, "opponent name": "C3-PO"}}